CHANGES.rst
CONTRIBUTORS.rst
DEVELOP.rst
LICENSE.rst
MANIFEST.in
README.md
setup.cfg
setup.py
docs/conf.py
docs/index.rst
src/zopyx/__init__.py
src/zopyx.usersascontent.egg-info/PKG-INFO
src/zopyx.usersascontent.egg-info/SOURCES.txt
src/zopyx.usersascontent.egg-info/dependency_links.txt
src/zopyx.usersascontent.egg-info/entry_points.txt
src/zopyx.usersascontent.egg-info/namespace_packages.txt
src/zopyx.usersascontent.egg-info/not-zip-safe
src/zopyx.usersascontent.egg-info/requires.txt
src/zopyx.usersascontent.egg-info/top_level.txt
src/zopyx/usersascontent/.adapters.py.swp
src/zopyx/usersascontent/__init__.py
src/zopyx/usersascontent/adapters.py
src/zopyx/usersascontent/configure.zcml
src/zopyx/usersascontent/interfaces.py
src/zopyx/usersascontent/permissions.zcml
src/zopyx/usersascontent/setuphandlers.py
src/zopyx/usersascontent/testing.py
src/zopyx/usersascontent/browser/__init__.py
src/zopyx/usersascontent/browser/configure.zcml
src/zopyx/usersascontent/browser/controlpanel.py
src/zopyx/usersascontent/browser/dashboard.py
src/zopyx/usersascontent/browser/view.pt
src/zopyx/usersascontent/browser/view2.pt
src/zopyx/usersascontent/browser/xx
src/zopyx/usersascontent/browser/overrides/.gitkeep
src/zopyx/usersascontent/browser/static/.gitkeep
src/zopyx/usersascontent/content/__init__.py
src/zopyx/usersascontent/content/plone_user.py
src/zopyx/usersascontent/content/plone_user.xml
src/zopyx/usersascontent/locales/README.rst
src/zopyx/usersascontent/locales/__init__.py
src/zopyx/usersascontent/locales/update.py
src/zopyx/usersascontent/locales/update.sh
src/zopyx/usersascontent/locales/zopyx.usersascontent.pot
src/zopyx/usersascontent/locales/de/LC_MESSAGES/zopyx.usersascontent.mo
src/zopyx/usersascontent/locales/de/LC_MESSAGES/zopyx.usersascontent.po
src/zopyx/usersascontent/locales/en/LC_MESSAGES/zopyx.usersascontent.mo
src/zopyx/usersascontent/locales/en/LC_MESSAGES/zopyx.usersascontent.po
src/zopyx/usersascontent/profiles/default/actions.xml
src/zopyx/usersascontent/profiles/default/browserlayer.xml
src/zopyx/usersascontent/profiles/default/catalog.xml
src/zopyx/usersascontent/profiles/default/controlpanel.xml
src/zopyx/usersascontent/profiles/default/metadata.xml
src/zopyx/usersascontent/profiles/default/registry.xml
src/zopyx/usersascontent/profiles/default/rolemap.xml
src/zopyx/usersascontent/profiles/default/types.xml
