Metadata-Version: 2.1
Name: zopyx.usersascontent
Version: 1.0a1
Summary: Plone users as content
Home-page: https://github.com/collective/zopyx.usersascontent
Author: Andreas Jung
Author-email: info@zopyx.com
License: GPL version 2
Project-URL: PyPI, https://pypi.python.org/pypi/zopyx.usersascontent
Project-URL: Source, https://github.com/collective/zopyx.usersascontent
Project-URL: Tracker, https://github.com/collective/zopyx.usersascontent/issues
Keywords: Python Plone CMS
Platform: UNKNOWN
Classifier: Environment :: Web Environment
Classifier: Framework :: Plone
Classifier: Framework :: Plone :: Addon
Classifier: Framework :: Plone :: 6.0
Classifier: Programming Language :: Python
Classifier: Programming Language :: Python :: 3.8
Classifier: Programming Language :: Python :: 3.9
Classifier: Operating System :: OS Independent
Classifier: License :: OSI Approved :: GNU General Public License v2 (GPLv2)
Requires-Python: >=3.8
Provides-Extra: test
